magentic_ui/__init__.py
magentic_ui/_cli.py
magentic_ui/_docker.py
magentic_ui/approval_guard.py
magentic_ui/guarded_action.py
magentic_ui/input_func.py
magentic_ui/magentic_ui_config.py
magentic_ui/task_team.py
magentic_ui/types.py
magentic_ui/utils.py
magentic_ui/version.py
magentic_ui/agents/__init__.py
magentic_ui/agents/_coder.py
magentic_ui/agents/_user_proxy.py
magentic_ui/agents/_utils.py
magentic_ui/agents/file_surfer/__init__.py
magentic_ui/agents/file_surfer/_browser_code_helpers.py
magentic_ui/agents/file_surfer/_code_markdown_file_browser.py
magentic_ui/agents/file_surfer/_file_surfer.py
magentic_ui/agents/file_surfer/_tool_definitions.py
magentic_ui/agents/mcp/__init__.py
magentic_ui/agents/mcp/_agent.py
magentic_ui/agents/mcp/_config.py
magentic_ui/agents/users/__init__.py
magentic_ui/agents/users/_dummy_user_proxy.py
magentic_ui/agents/users/_metadata_user_proxy.py
magentic_ui/agents/web_surfer/__init__.py
magentic_ui/agents/web_surfer/_cua_web_surfer.py
magentic_ui/agents/web_surfer/_events.py
magentic_ui/agents/web_surfer/_prompts.py
magentic_ui/agents/web_surfer/_set_of_mark.py
magentic_ui/agents/web_surfer/_tool_definitions.py
magentic_ui/agents/web_surfer/_web_surfer.py
magentic_ui/agents/web_surfer/.claude/settings.local.json
magentic_ui/backend/__init__.py
magentic_ui/backend/cli.py
magentic_ui/backend/.claude/settings.local.json
magentic_ui/backend/database/__init__.py
magentic_ui/backend/database/db_manager.py
magentic_ui/backend/database/schema_manager.py
magentic_ui/backend/datamodel/__init__.py
magentic_ui/backend/datamodel/db.py
magentic_ui/backend/datamodel/types.py
magentic_ui/backend/teammanager/__init__.py
magentic_ui/backend/teammanager/teammanager.py
magentic_ui/backend/utils/__init__.py
magentic_ui/backend/utils/utils.py
magentic_ui/backend/web/__init__.py
magentic_ui/backend/web/app.py
magentic_ui/backend/web/config.py
magentic_ui/backend/web/deps.py
magentic_ui/backend/web/initialization.py
magentic_ui-0.1.5.dist-info/METADATA
magentic_ui-0.1.5.dist-info/WHEEL
magentic_ui-0.1.5.dist-info/entry_points.txt
magentic_ui-0.1.5.dist-info/licenses/LICENSE
magentic_ui-0.1.5.dist-info/RECORD
