Metadata-Version: 2.4
Name: magentic_ui
Version: 0.1.5
Summary: A research prototype of a human-centered interface powered by a multi-agent system
Project-URL: Homepage, https://github.com/microsoft/magentic-ui
Project-URL: Repository, https://github.com/microsoft/magentic-ui
Project-URL: Issues, https://github.com/microsoft/magentic-ui/issues
Author-email: Microsoft Corporation <magui@service.microsoft.com>
License-Expression: MIT
License-File: LICENSE
Keywords: agents,ai-assistant,browser-use,multi-agent,playwright,web-automation
Classifier: Development Status :: 3 - Alpha
Classifier: Intended Audience :: Developers
Classifier: Intended Audience :: Science/Research
Classifier: License :: OSI Approved :: MIT License
Classifier: Operating System :: OS Independent
Classifier: Programming Language :: Python :: 3
Classifier: Topic :: Internet :: WWW/HTTP :: Browsers
Classifier: Topic :: Scientific/Engineering :: Artificial Intelligence
Classifier: Topic :: Software Development :: Libraries :: Python Modules
Requires-Python: >=3.10
Requires-Dist: aioconsole
Requires-Dist: aiofiles
Requires-Dist: aiohttp
Requires-Dist: alembic
Requires-Dist: autogen-agentchat==0.5.7
Requires-Dist: autogen-core==0.5.7
Requires-Dist: autogen-ext[docker,file-surfer,magentic-one,mcp,openai,task-centric-memory,web-surfer]==0.5.7
Requires-Dist: docker
Requires-Dist: fastapi[standard]
Requires-Dist: html2text
Requires-Dist: loguru
Requires-Dist: nest-asyncio
Requires-Dist: playwright==1.51
Requires-Dist: psutil
Requires-Dist: psycopg
Requires-Dist: pydantic
Requires-Dist: pydantic-settings
Requires-Dist: python-dotenv
Requires-Dist: pyyaml
Requires-Dist: sqlmodel
Requires-Dist: tldextract
Requires-Dist: typer
Requires-Dist: websockets
Provides-Extra: azure
Requires-Dist: autogen-ext[azure]==0.5.7; extra == 'azure'
Provides-Extra: eval
Requires-Dist: huggingface-hub; extra == 'eval'
Requires-Dist: pandas; extra == 'eval'
Requires-Dist: scipy; extra == 'eval'
Provides-Extra: ollama
Requires-Dist: autogen-ext[ollama]==0.5.7; extra == 'ollama'
